wrap_your_gym/__init__.py
wrap_your_gym/dict_wrappers.py
wrap_your_gym/py.typed
wrap_your_gym/torch_wrappers.py
wrap_your_gym-0.0.2.dist-info/LICENSE
wrap_your_gym-0.0.2.dist-info/WHEEL
wrap_your_gym-0.0.2.dist-info/METADATA
wrap_your_gym-0.0.2.dist-info/RECORD
