Metadata-Version: 2.1
Name: wrap-your-gym
Version: 0.0.2
Summary: Common OpenAI Gym Wrappers
Home-page: https://github.com/sebimarkgraf/wrap-your-gym
License: BSD-3-Clause
Author: Sebastian Markgraf
Author-email: sebastian-markgraf@t-online.de
Requires-Python: >=3.7.0,<4.0
Classifier: Development Status :: 4 - Beta
Classifier: Environment :: Web Environment
Classifier: Intended Audience :: Developers
Classifier: License :: OSI Approved :: BSD License
Classifier: Operating System :: OS Independent
Classifier: Programming Language :: Python
Classifier: Programming Language :: Python :: 3
Classifier: Programming Language :: Python :: 3.7
Classifier: Programming Language :: Python :: 3.8
Classifier: Programming Language :: Python :: 3.9
Classifier: Programming Language :: Python :: 3.10
Classifier: Programming Language :: Python :: 3.11
Classifier: Programming Language :: Python :: 3
Classifier: Programming Language :: Python :: 3.6
Classifier: Programming Language :: Python :: 3.7
Classifier: Programming Language :: Python :: 3.8
Classifier: Programming Language :: Python :: 3.9
Classifier: Topic :: Software Development :: Libraries :: Python Modules
Classifier: Typing :: Typed
Provides-Extra: torch
Requires-Dist: gym (>0.20.0)
Project-URL: Documentation, https://github.com/sebimarkgraf/wrap-your-gym/blob/main/README.md
Project-URL: Repository, https://github.com/sebimarkgraf/wrap-your-gym
